INSTALL.txt
README.txt
buildout.cfg
setup.py
test.py
icu/README.txt
icu/setup.py
icu/src/zc/__init__.py
icu/src/zc/recipe/__init__.py
icu/src/zc/recipe/icu/__init__.py
src/zope/__init__.py
src/zope.ucol.egg-info/PKG-INFO
src/zope.ucol.egg-info/SOURCES.txt
src/zope.ucol.egg-info/dependency_links.txt
src/zope.ucol.egg-info/not-zip-safe
src/zope.ucol.egg-info/top_level.txt
src/zope/ucol/README.txt
src/zope/ucol/__init__.py
src/zope/ucol/_zope_ucol.c
src/zope/ucol/_zope_ucol.pyx
src/zope/ucol/localeadapter.py
src/zope/ucol/tests.py
