Metadata-Version: 1.0
Name: zope.ucol
Version: 1.0.2
Summary: Python access to ICU text collation
Home-page: http://www.python.org/pypi/zope.ucol
Author: Jim Fulton
Author-email: jim@zope.com
License: ZPL 2.1
Keywords: internationalization
Platform: UNKNOWN
Classifier: Development Status :: 5 - Production/Stable
Classifier: Intended Audience :: Developers
Classifier: License :: OSI Approved :: Zope Public License
Classifier: Topic :: Software Development :: Libraries :: Python Modules
Classifier: Topic :: Software Development :: Internationalization
